voici_core/__init__.py
voici_core/__main__.py
voici_core/_version.py
voici_core/addon.py
voici_core/app.py
voici_core/exporter.py
voici_core/tree_exporter.py
voici_core/static/index.html
voici_core/static/build/1043.js
voici_core/static/build/1060.js
voici_core/static/build/1259.js
voici_core/static/build/1373.js
voici_core/static/build/1392.js
voici_core/static/build/1433.js
voici_core/static/build/1449.js
voici_core/static/build/1449.js.LICENSE.txt
voici_core/static/build/1462.js
voici_core/static/build/1483.js
voici_core/static/build/1581.js
voici_core/static/build/1601.js
voici_core/static/build/1621.js
voici_core/static/build/1650.js
voici_core/static/build/1664.js
voici_core/static/build/1670.js
voici_core/static/build/1814.js
voici_core/static/build/1819.js
voici_core/static/build/1863.js
voici_core/static/build/1883.js
voici_core/static/build/1908.js
voici_core/static/build/1908.js.LICENSE.txt
voici_core/static/build/1963.js
voici_core/static/build/1996.js
voici_core/static/build/1996.js.LICENSE.txt
voici_core/static/build/1cb1c39ea642f26a4dfe.woff
voici_core/static/build/206.js
voici_core/static/build/2094.js
voici_core/static/build/2121.js
voici_core/static/build/225.js
voici_core/static/build/2296.js
voici_core/static/build/2345.js
voici_core/static/build/2357.js
voici_core/static/build/2360.js
voici_core/static/build/2395.js
voici_core/static/build/2407.js
voici_core/static/build/2552.js
voici_core/static/build/2649.js
voici_core/static/build/26683bf201fb258a2237.woff
voici_core/static/build/2679.js
voici_core/static/build/2717.js
voici_core/static/build/2772.js
voici_core/static/build/2779.js
voici_core/static/build/2812.js
voici_core/static/build/2829.js
voici_core/static/build/2842.js
voici_core/static/build/2906.js
voici_core/static/build/2915.js
voici_core/static/build/2929.js
voici_core/static/build/299.js
voici_core/static/build/3082.js
voici_core/static/build/30e889b58cbc51adfbb0.woff
voici_core/static/build/3144.js
voici_core-0.10.0.dist-info/METADATA
voici_core-0.10.0.dist-info/WHEEL
voici_core-0.10.0.dist-info/entry_points.txt
voici_core-0.10.0.dist-info/licenses/LICENSE
voici_core-0.10.0.dist-info/RECORD
