Metadata-Version: 2.4
Name: voici-core
Version: 0.10.0
Summary: Voici turns Jupyter notebooks into static web applications
Project-URL: Homepage, https://github.com/voila-dashboards/voici
Author: Voila Development Team
License: BSD License
License-File: LICENSE
Keywords: Emscripten,Jupyter,JupyterLite,Voici,Voila
Classifier: Framework :: Jupyter
Classifier: License :: OSI Approved :: BSD License
Classifier: Programming Language :: Python
Classifier: Programming Language :: Python :: 3
Classifier: Programming Language :: Python :: 3.10
Classifier: Programming Language :: Python :: 3.11
Classifier: Programming Language :: Python :: 3.12
Classifier: Programming Language :: Python :: 3.13
Classifier: Programming Language :: Python :: 3.14
Requires-Python: >=3.10
Requires-Dist: jupyterlite-core<0.8.0,>=0.7.0
Requires-Dist: voila<0.6,>=0.5.5
Provides-Extra: dev
Requires-Dist: hatch; extra == 'dev'
Requires-Dist: ruff<0.12,>=0.11; extra == 'dev'
